{"get": "players", "parameters": {"team": "8", "season": "2025"}, "errors": [], "results": 56, "response": [{"id": 115, "name": "Caleb Johnson", "age": 27, "height": "6' 2\"", "weight": "220 lbs", "college": "Houston Christian", "group": "Defense", "position": "LB", "number": 53, "salary": "-", "experience": 5, "image": "https://media.api-sports.io/american-football/players/115.png"}, {"id": 128, "name": "Josh Thompson", "age": 26, "height": "6' 0\"", "weight": "191 lbs", "college": "Texas", "group": "Defense", "position": "S", "number": 45, "salary": "-", "experience": 2, "image": "https://media.api-sports.io/american-football/players/128.png"}, {"id": 192, "name": "Ronnie Perkins", "age": 25, "height": "6' 3\"", "weight": "253 lbs", "college": "Oklahoma", "group": "Practice Squad", "position": "LB", "number": 57, "salary": null, "experience": 4, "image": "https://media.api-sports.io/american-football/players/192.png"}, {"id": 233, "name": "David Sills V", "age": 29, "height": "6' 3\"", "weight": "211 lbs", "college": "West Virginia", "group": "Offense", "position": "WR", "number": 87, "salary": null, "experience": 3, "image": "https://media.api-sports.io/american-football/players/233.png"}, {"id": 460, "name": "DJ Chark", "age": 28, "height": "6' 3\"", "weight": "198 lbs", "college": "LSU", "group": "Offense", "position": "WR", "number": 16, "salary": "-", "experience": 8, "image": "https://media.api-sports.io/american-football/players/460.png"}, {"id": 507, "name": "Josh Woods", "age": 29, "height": "6' 1\"", "weight": "235 lbs", "college": "Maryland", "group": "Defense", "position": "LB", "number": 42, "salary": "-", "experience": 6, "image": "https://media.api-sports.io/american-football/players/507.png"}, {"id": 526, "name": "Feleipe Franks", "age": 27, "height": "6' 6\"", "weight": "241 lbs", "college": "Arkansas", "group": "Offense", "position": "TE", "number": 84, "salary": "-", "experience": 3, "image": "https://media.api-sports.io/american-football/players/526.png"}, {"id": 564, "name": "Arnold Ebiketie", "age": 26, "height": "6' 2\"", "weight": "250 lbs", "college": "Penn State", "group": "Defense", "position": "LB", "number": 17, "salary": "-", "experience": 4, "image": "https://media.api-sports.io/american-football/players/564.png"}, {"id": 569, "name": "Ta'Quon Graham", "age": 26, "height": "6' 4\"", "weight": "300 lbs", "college": "Texas", "group": "Injured Reserve Or O", "position": "DT", "number": 95, "salary": "-", "experience": 5, "image": "https://media.api-sports.io/american-football/players/569.png"}, {"id": 583, "name": "DeAngelo Malone", "age": 26, "height": "6' 3\"", "weight": "235 lbs", "college": "Western Kentucky", "group": "Defense", "position": "LB", "number": 51, "salary": "-", "experience": 4, "image": "https://media.api-sports.io/american-football/players/583.png"}, {"id": 586, "name": "Dee Alford", "age": 27, "height": "5' 11\"", "weight": "180 lbs", "college": "Tusculum", "group": "Defense", "position": "CB", "number": 20, "salary": "-", "experience": 4, "image": "https://media.api-sports.io/american-football/players/586.png"}, {"id": 587, "name": "Mike Ford", "age": 30, "height": "6' 0\"", "weight": "199 lbs", "college": "Southeast Missouri State", "group": "Defense", "position": "CB", "number": 28, "salary": null, "experience": 8, "image": "https://media.api-sports.io/american-football/players/587.png"}, {"id": 601, "name": "Younghoe Koo", "age": 31, "height": "5' 10\"", "weight": "195 lbs", "college": "Georgia Southern", "group": "Special Teams", "position": "PK", "number": 6, "salary": "-", "experience": 8, "image": "https://media.api-sports.io/american-football/players/601.png"}, {"id": 602, "name": "Bradley Pinion", "age": 31, "height": "6' 5\"", "weight": "265 lbs", "college": "Clemson", "group": "Special Teams", "position": "P", "number": 13, "salary": "-", "experience": 11, "image": "https://media.api-sports.io/american-football/players/602.png"}, {"id": 604, "name": "Liam McCullough", "age": 28, "height": "6' 2\"", "weight": "245 lbs", "college": "Ohio State", "group": "Special Teams", "position": "LS", "number": 49, "salary": "-", "experience": 3, "image": "https://media.api-sports.io/american-football/players/604.png"}, {"id": 676, "name": "Ronnie Harrison Jr.", "age": 28, "height": "6' 2\"", "weight": "207 lbs", "college": "Alabama", "group": "Practice Squad", "position": "S", "number": 36, "salary": null, "experience": 8, "image": "https://media.api-sports.io/american-football/players/676.png"}, {"id": 717, "name": "Khalid Kareem", "age": 27, "height": "6' 4\"", "weight": "255 lbs", "college": "Notre Dame", "group": "Practice Squad", "position": "LB", "number": 92, "salary": null, "experience": 4, "image": "https://media.api-sports.io/american-football/players/717.png"}, {"id": 1182, "name": "Lamar Jackson", "age": 27, "height": "6' 2\"", "weight": "212 lbs", "college": "Nebraska", "group": "Defense", "position": "CB", "number": 38, "salary": "-", "experience": 3, "image": "https://media.api-sports.io/american-football/players/1182.png"}, {"id": 1399, "name": "CJ Henderson", "age": 26, "height": "6' 1\"", "weight": "205 lbs", "college": "Florida", "group": "Practice Squad", "position": "CB", "number": 30, "salary": null, "experience": 6, "image": "https://media.api-sports.io/american-football/players/1399.png"}, {"id": 1402, "name": "Keith Taylor Jr.", "age": 26, "height": "6' 3\"", "weight": "195 lbs", "college": "Washington", "group": "Defense", "position": "CB", "number": 39, "salary": "-", "experience": 4, "image": "https://media.api-sports.io/american-football/players/1402.png"}, {"id": 1506, "name": "Nikola Kalinic", "age": 28, "height": "6' 4\"", "weight": "248 lbs", "college": null, "group": "Practice Squad", "position": "TE", "number": 0, "salary": null, "experience": 2, "image": "https://media.api-sports.io/american-football/players/1506.png"}, {"id": 1550, "name": "Henry Black", "age": 28, "height": "6' 0\"", "weight": "204 lbs", "college": "Baylor", "group": "Defense", "position": "S", "number": 32, "salary": "-", "experience": 3, "image": "https://media.api-sports.io/american-football/players/1550.png"}, {"id": 1871, "name": "Teagan Quitoriano", "age": 25, "height": "6' 6\"", "weight": "259 lbs", "college": "Oregon State", "group": "Offense", "position": "TE", "number": 85, "salary": "-", "experience": 4, "image": "https://media.api-sports.io/american-football/players/1871.png"}, {"id": 1972, "name": "Kentavius Street", "age": 29, "height": "6' 2\"", "weight": "315 lbs", "college": "NC State", "group": "Practice Squad", "position": "DT", "number": 93, "salary": null, "experience": 7, "image": "https://media.api-sports.io/american-football/players/1972.png"}, {"id": 2152, "name": "Easton Stick", "age": 29, "height": "6' 1\"", "weight": "224 lbs", "college": "North Dakota State", "group": "Practice Squad", "position": "QB", "number": 12, "salary": null, "experience": 6, "image": "https://media.api-sports.io/american-football/players/2152.png"}, {"id": 2187, "name": "Morgan Fox", "age": 30, "height": "6' 3\"", "weight": "275 lbs", "college": "Colorado State-Pueblo", "group": "Defense", "position": "DE", "number": 99, "salary": "-", "experience": 9, "image": "https://media.api-sports.io/american-football/players/2187.png"}, {"id": 2299, "name": "Jordan Fuller", "age": 27, "height": "6' 2\"", "weight": "203 lbs", "college": "Ohio State", "group": "Defense", "position": "S", "number": 29, "salary": "-", "experience": 6, "image": "https://media.api-sports.io/american-football/players/2299.png"}, {"id": 2543, "name": "Jashaun Corbin", "age": 25, "height": "5' 11\"", "weight": "200 lbs", "college": "Florida State", "group": "Offense", "position": "RB", "number": 30, "salary": "-", "experience": 2, "image": "https://media.api-sports.io/american-football/players/2543.png"}, {"id": 2696, "name": "Ben DiNucci", "age": 28, "height": "6' 2\"", "weight": "215 lbs", "college": "James Madison", "group": "Offense", "position": "QB", "number": 15, "salary": null, "experience": 2, "image": "https://media.api-sports.io/american-football/players/2696.png"}, {"id": 2870, "name": "LaCale London", "age": 28, "height": "6' 3\"", "weight": "297 lbs", "college": "Western Illinois", "group": "Defense", "position": "DE", "number": 94, "salary": "-", "experience": 2, "image": "https://media.api-sports.io/american-football/players/2870.png"}, {"id": 3131, "name": "Chris Blair", "age": 27, "height": "6' 2\"", "weight": "215 lbs", "college": "Alcorn State", "group": "Practice Squad", "position": "WR", "number": 19, "salary": null, "experience": 2, "image": "https://media.api-sports.io/american-football/players/3131.png"}, {"id": 6403, "name": "Joshua Simon", "age": 24, "height": "6' 4\"", "weight": "240 lbs", "college": "South Carolina", "group": "Practice Squad", "position": "TE", "number": 47, "salary": null, "experience": null, "image": "https://media.api-sports.io/american-football/players/6403.png"}, {"id": 7183, "name": "Nathan Carter", "age": 23, "height": "5' 10\"", "weight": "202 lbs", "college": "Michigan State", "group": "Offense", "position": "RB", "number": 38, "salary": null, "experience": null, "image": "https://media.api-sports.io/american-football/players/7183.png"}, {"id": 8840, "name": "Quincy Skinner Jr.", "age": 22, "height": "6' 2\"", "weight": "205 lbs", "college": "Vanderbilt", "group": "Offense", "position": "WR", "number": 36, "salary": "-", "experience": null, "image": "https://media.api-sports.io/american-football/players/8840.png"}, {"id": 9938, "name": "James Pearce Jr.", "age": 21, "height": "6' 5\"", "weight": "243 lbs", "college": "Tennessee", "group": "Defense", "position": "LB", "number": 27, "salary": "-", "experience": null, "image": "https://media.api-sports.io/american-football/players/9938.png"}, {"id": 11835, "name": "Emory Jones", "age": 25, "height": "6' 2\"", "weight": "211 lbs", "college": "Cincinnati", "group": "Injured Reserve Or O", "position": "QB", "number": 15, "salary": "-", "experience": 1, "image": "https://media.api-sports.io/american-football/players/11835.png"}, {"id": 12272, "name": "Nick Nash", "age": 26, "height": "6' 3\"", "weight": "195 lbs", "college": "San Jos\u00c3\u00a9 State", "group": "Practice Squad", "position": "WR", "number": 80, "salary": null, "experience": null, "image": "https://media.api-sports.io/american-football/players/12272.png"}, {"id": 12554, "name": "Simeon Barrow", "age": 23, "height": "6' 3\"", "weight": "283 lbs", "college": "Miami", "group": "Defense", "position": "DE", "number": 91, "salary": null, "experience": null, "image": "https://media.api-sports.io/american-football/players/12554.png"}, {"id": 12730, "name": "Dylan Drummond", "age": 25, "height": "6' 0\"", "weight": "190 lbs", "college": "Eastern Michigan", "group": "Practice Squad", "position": "WR", "number": 81, "salary": null, "experience": 1, "image": "https://media.api-sports.io/american-football/players/12730.png"}, {"id": 13590, "name": "Jacobee Bryant", "age": 23, "height": "6' 0\"", "weight": "180 lbs", "college": "Kansas", "group": "Practice Squad", "position": "CB", "number": 37, "salary": null, "experience": null, "image": "https://media.api-sports.io/american-football/players/13590.png"}, {"id": 14200, "name": "DeMarcco Hellams", "age": 25, "height": "6' 1\"", "weight": "203 lbs", "college": "Alabama", "group": "Defense", "position": "S", "number": 23, "salary": "-", "experience": 3, "image": "https://media.api-sports.io/american-football/players/14200.png"}, {"id": 14292, "name": "Zach Harrison", "age": 24, "height": "6' 5\"", "weight": "270 lbs", "college": "Ohio State", "group": "Defense", "position": "DE", "number": 96, "salary": "-", "experience": 3, "image": "https://media.api-sports.io/american-football/players/14292.png"}, {"id": 14422, "name": "JD Bertrand", "age": 25, "height": "6' 1\"", "weight": "230 lbs", "college": "Notre Dame", "group": "Defense", "position": "LB", "number": 40, "salary": "-", "experience": 2, "image": "https://media.api-sports.io/american-football/players/14422.png"}, {"id": 14450, "name": "Xavier Watts", "age": 23, "height": "6' 0\"", "weight": "203 lbs", "college": "Notre Dame", "group": "Defense", "position": "S", "number": 31, "salary": "-", "experience": null, "image": "https://media.api-sports.io/american-football/players/14450.png"}, {"id": 14558, "name": "Jalon Walker", "age": 21, "height": "6' 2\"", "weight": "245 lbs", "college": "Georgia", "group": "Defense", "position": "LB", "number": 11, "salary": "-", "experience": null, "image": "https://media.api-sports.io/american-football/players/14558.png"}, {"id": 14660, "name": "Brandon Dorlus", "age": 24, "height": "6' 3\"", "weight": "295 lbs", "college": "Oregon", "group": "Defense", "position": "DT", "number": 54, "salary": "-", "experience": 2, "image": "https://media.api-sports.io/american-football/players/14660.png"}, {"id": 14699, "name": "Dontae Manning", "age": 23, "height": "5' 10\"", "weight": "190 lbs", "college": "Oregon", "group": "Practice Squad", "position": "CB", "number": 0, "salary": null, "experience": null, "image": "https://media.api-sports.io/american-football/players/14699.png"}, {"id": 15425, "name": "Billy Bowman", "age": 22, "height": "5' 10\"", "weight": "194 lbs", "college": "Oklahoma", "group": "Defense", "position": "S", "number": 33, "salary": "-", "experience": null, "image": "https://media.api-sports.io/american-football/players/15425.png"}, {"id": 19768, "name": "Jesse Matthews", "age": 26, "height": "6' 0\"", "weight": "190 lbs", "college": "San Diego State", "group": "Offense", "position": "WR", "number": 86, "salary": "-", "experience": 2, "image": "https://media.api-sports.io/american-football/players/19768.png"}, {"id": 20472, "name": "Matthew Cindric", "age": 26, "height": "6' 4\"", "weight": "295 lbs", "college": "California", "group": "Offense", "position": "C", "number": 73, "salary": null, "experience": 1, "image": "https://media.api-sports.io/american-football/players/20472.png"}, {"id": 22502, "name": "Natrone Brooks", "age": 25, "height": "5' 11\"", "weight": "175 lbs", "college": "Southern Miss", "group": "Defense", "position": "CB", "number": 35, "salary": "-", "experience": 2, "image": "https://media.api-sports.io/american-football/players/22502.png"}, {"id": 25599, "name": "Bralen Trice", "age": 24, "height": "6' 4\"", "weight": "274 lbs", "college": "Washington", "group": "Injured Reserve Or O", "position": "LB", "number": 48, "salary": "-", "experience": 2, "image": "https://media.api-sports.io/american-football/players/25599.png"}, {"id": 26054, "name": "Ruke Orhorhoro", "age": 23, "height": "6' 4\"", "weight": "295 lbs", "college": "Clemson", "group": "Defense", "position": "DT", "number": 98, "salary": "-", "experience": 2, "image": "https://media.api-sports.io/american-football/players/26054.png"}, {"id": 27206, "name": "Elijah Dotson", "age": 26, "height": "5' 9\"", "weight": "202 lbs", "college": "Northern Colorado", "group": "Offense", "position": "RB", "number": 41, "salary": "-", "experience": 2, "image": "https://media.api-sports.io/american-football/players/27206.png"}, {"id": 30782, "name": "Nick Kubitz", "age": 24, "height": "6' 3\"", "weight": "229 lbs", "college": "North Dakota State", "group": "Defense", "position": "LB", "number": 59, "salary": "-", "experience": null, "image": "https://media.api-sports.io/american-football/players/30782.png"}, {"id": 59048, "name": "Lenny Krieg", "age": 23, "height": "6' 2\"", "weight": "214 lbs", "college": null, "group": "Practice Squad", "position": "PK", "number": 46, "salary": null, "experience": null, "image": "https://media.api-sports.io/american-football/players/59048.png"}]}