{"get": "players", "parameters": {"team": "21", "season": "2025"}, "errors": [], "results": 64, "response": [{"id": 126, "name": "Tre Herndon", "age": 29, "height": "5' 11\"", "weight": "185 lbs", "college": "Vanderbilt", "group": "Defense", "position": "S", "number": 38, "salary": "-", "experience": 7, "image": "https://media.api-sports.io/american-football/players/126.png"}, {"id": 158, "name": "Laquon Treadwell", "age": 30, "height": "6' 2\"", "weight": "215 lbs", "college": "Ole Miss", "group": "Practice Squad", "position": "WR", "number": 13, "salary": null, "experience": 9, "image": "https://media.api-sports.io/american-football/players/158.png"}, {"id": 190, "name": "Cameron McGrone", "age": 25, "height": "6' 1\"", "weight": "236 lbs", "college": "Michigan", "group": "Defense", "position": "LB", "number": 59, "salary": "-", "experience": 3, "image": "https://media.api-sports.io/american-football/players/190.png"}, {"id": 216, "name": "Daniel Jones", "age": 28, "height": "6' 5\"", "weight": "230 lbs", "college": "Duke", "group": "Offense", "position": "QB", "number": 17, "salary": "-", "experience": 7, "image": "https://media.api-sports.io/american-football/players/216.png"}, {"id": 724, "name": "Josh Tupou", "age": 31, "height": "6' 3\"", "weight": "340 lbs", "college": "Colorado", "group": "Practice Squad", "position": "DT", "number": 69, "salary": null, "experience": 7, "image": "https://media.api-sports.io/american-football/players/724.png"}, {"id": 725, "name": "Joe Bachie", "age": 27, "height": "6' 2\"", "weight": "235 lbs", "college": "Michigan State", "group": "Defense", "position": "LB", "number": 48, "salary": "-", "experience": 6, "image": "https://media.api-sports.io/american-football/players/725.png"}, {"id": 1040, "name": "Samuel Womack III", "age": 26, "height": "5' 10\"", "weight": "189 lbs", "college": "Toledo", "group": "Defense", "position": "CB", "number": 0, "salary": null, "experience": 4, "image": "https://media.api-sports.io/american-football/players/1040.png"}, {"id": 1052, "name": "Tyler Goodson", "age": 24, "height": "5' 9\"", "weight": "197 lbs", "college": "Iowa", "group": "Offense", "position": "RB", "number": 31, "salary": "-", "experience": 3, "image": "https://media.api-sports.io/american-football/players/1052.png"}, {"id": 1125, "name": "Khalil Herbert", "age": 27, "height": "5' 9\"", "weight": "212 lbs", "college": "Virginia Tech", "group": "Practice Squad", "position": "RB", "number": 26, "salary": null, "experience": 5, "image": "https://media.api-sports.io/american-football/players/1125.png"}, {"id": 1246, "name": "Chris Lammons", "age": 29, "height": "5' 10\"", "weight": "190 lbs", "college": "South Carolina", "group": "Practice Squad", "position": "CB", "number": 38, "salary": null, "experience": 5, "image": "https://media.api-sports.io/american-football/players/1246.png"}, {"id": 1494, "name": "Jonathan Taylor", "age": 26, "height": "5' 10\"", "weight": "226 lbs", "college": "Wisconsin", "group": "Offense", "position": "RB", "number": 28, "salary": "-", "experience": 6, "image": "https://media.api-sports.io/american-football/players/1494.png"}, {"id": 1497, "name": "Ashton Dulin", "age": 28, "height": "6' 2\"", "weight": "215 lbs", "college": "Malone", "group": "Offense", "position": "WR", "number": 16, "salary": "-", "experience": 7, "image": "https://media.api-sports.io/american-football/players/1497.png"}, {"id": 1501, "name": "Michael Pittman Jr.", "age": 27, "height": "6' 4\"", "weight": "223 lbs", "college": "USC", "group": "Offense", "position": "WR", "number": 11, "salary": "-", "experience": 6, "image": "https://media.api-sports.io/american-football/players/1501.png"}, {"id": 1503, "name": "Mo Alie-Cox", "age": 31, "height": "6' 5\"", "weight": "267 lbs", "college": "VCU", "group": "Offense", "position": "TE", "number": 81, "salary": "-", "experience": 8, "image": "https://media.api-sports.io/american-football/players/1503.png"}, {"id": 1507, "name": "Andrew Ogletree", "age": 27, "height": "6' 5\"", "weight": "260 lbs", "college": "Youngstown State", "group": "Offense", "position": "TE", "number": 85, "salary": null, "experience": 4, "image": "https://media.api-sports.io/american-football/players/1507.png"}, {"id": 1508, "name": "Jelani Woods", "age": 26, "height": "6' 7\"", "weight": "253 lbs", "college": "Virginia", "group": "Offense", "position": "TE", "number": 0, "salary": "-", "experience": 4, "image": "https://media.api-sports.io/american-football/players/1508.png"}, {"id": 1527, "name": "Kwity Paye", "age": 26, "height": "6' 3\"", "weight": "265 lbs", "college": "Michigan", "group": "Defense", "position": "DE", "number": 51, "salary": "-", "experience": 5, "image": "https://media.api-sports.io/american-football/players/1527.png"}, {"id": 1531, "name": "Eric Johnson", "age": 27, "height": "6' 4\"", "weight": "320 lbs", "college": "Missouri State", "group": "Defense", "position": "DT", "number": 98, "salary": null, "experience": 4, "image": "https://media.api-sports.io/american-football/players/1531.png"}, {"id": 1533, "name": "Grover Stewart", "age": 31, "height": "6' 4\"", "weight": "314 lbs", "college": "Albany State", "group": "Defense", "position": "DT", "number": 90, "salary": "-", "experience": 9, "image": "https://media.api-sports.io/american-football/players/1533.png"}, {"id": 1539, "name": "Segun Olubi", "age": 25, "height": "6' 1\"", "weight": "233 lbs", "college": "San Diego State", "group": "Defense", "position": "LB", "number": 50, "salary": "-", "experience": 3, "image": "https://media.api-sports.io/american-football/players/1539.png"}, {"id": 1556, "name": "Rodney Thomas II", "age": 27, "height": "6' 1\"", "weight": "196 lbs", "college": "Yale", "group": "Defense", "position": "S", "number": 25, "salary": null, "experience": 4, "image": "https://media.api-sports.io/american-football/players/1556.png"}, {"id": 1560, "name": "Rigoberto Sanchez", "age": 30, "height": "6' 0\"", "weight": "195 lbs", "college": "Hawai&#x27;i", "group": "Special Teams", "position": "P", "number": 8, "salary": "-", "experience": 9, "image": "https://media.api-sports.io/american-football/players/1560.png"}, {"id": 2096, "name": "Sean McKeon", "age": 27, "height": "6' 5\"", "weight": "255 lbs", "college": "Michigan", "group": "Practice Squad", "position": "TE", "number": 49, "salary": null, "experience": 5, "image": "https://media.api-sports.io/american-football/players/2096.png"}, {"id": 2121, "name": "Neville Gallimore", "age": 28, "height": "6' 2\"", "weight": "307 lbs", "college": "Oklahoma", "group": "Defense", "position": "DT", "number": 92, "salary": "-", "experience": 6, "image": "https://media.api-sports.io/american-football/players/2121.png"}, {"id": 2371, "name": "Duke Shelley", "age": 26, "height": "5' 8\"", "weight": "183 lbs", "college": "Kansas State", "group": "Defense", "position": "CB", "number": 23, "salary": "($500,000)", "experience": 5, "image": "https://media.api-sports.io/american-football/players/2371.png"}, {"id": 6591, "name": "Maddux Trujillo", "age": 22, "height": "6' 0\"", "weight": "172 lbs", "college": "Temple", "group": "Injured Reserve Or O", "position": "PK", "number": 48, "salary": "-", "experience": null, "image": "https://media.api-sports.io/american-football/players/6591.png"}, {"id": 6647, "name": "Adetomiwa Adebawore", "age": 24, "height": "6' 2\"", "weight": "282 lbs", "college": "Northwestern", "group": "Defense", "position": "DT", "number": 95, "salary": "-", "experience": 3, "image": "https://media.api-sports.io/american-football/players/6647.png"}, {"id": 6917, "name": "Austin Ajiake", "age": 25, "height": "6' 1\"", "weight": "223 lbs", "college": "UNLV", "group": "Practice Squad", "position": "LB", "number": 58, "salary": null, "experience": 1, "image": "https://media.api-sports.io/american-football/players/6917.png"}, {"id": 8185, "name": "Isaiah Land", "age": 25, "height": "6' 4\"", "weight": "235 lbs", "college": "Florida A&M", "group": "Defense", "position": "LB", "number": 0, "salary": null, "experience": 3, "image": "https://media.api-sports.io/american-football/players/8185.png"}, {"id": 9253, "name": "Solomon DeShields", "age": 23, "height": "6' 2\"", "weight": "235 lbs", "college": "Texas A&M", "group": "Defense", "position": "LB", "number": 53, "salary": null, "experience": null, "image": "https://media.api-sports.io/american-football/players/9253.png"}, {"id": 10922, "name": "Tyler Warren", "age": 23, "height": "6' 6\"", "weight": "256 lbs", "college": "Penn State", "group": "Offense", "position": "TE", "number": 84, "salary": "-", "experience": null, "image": "https://media.api-sports.io/american-football/players/10922.png"}, {"id": 11969, "name": "Coleman Owen", "age": 24, "height": "5' 10\"", "weight": "181 lbs", "college": "Ohio", "group": "Practice Squad", "position": "WR", "number": 3, "salary": null, "experience": null, "image": "https://media.api-sports.io/american-football/players/11969.png"}, {"id": 13005, "name": "Marcus Haynes", "age": 27, "height": "6' 4\"", "weight": "240 lbs", "college": "Old Dominion", "group": "Defense", "position": "DE", "number": 96, "salary": "-", "experience": 1, "image": "https://media.api-sports.io/american-football/players/13005.png"}, {"id": 13279, "name": "Riley Leonard", "age": 22, "height": "6' 4\"", "weight": "213 lbs", "college": "Notre Dame", "group": "Offense", "position": "QB", "number": 15, "salary": "-", "experience": null, "image": "https://media.api-sports.io/american-football/players/13279.png"}, {"id": 13501, "name": "Jason Bean", "age": 25, "height": "6' 2\"", "weight": "196 lbs", "college": "Kansas", "group": "Offense", "position": "QB", "number": 12, "salary": "-", "experience": 2, "image": "https://media.api-sports.io/american-football/players/13501.png"}, {"id": 14171, "name": "Tim Smith", "age": 23, "height": "6' 4\"", "weight": "302 lbs", "college": "Alabama", "group": "Defense", "position": "DT", "number": 93, "salary": "-", "experience": null, "image": "https://media.api-sports.io/american-football/players/14171.png"}, {"id": 14296, "name": "J.T. Tuimoloau", "age": 22, "height": "6' 4\"", "weight": "264 lbs", "college": "Ohio State", "group": "Defense", "position": "DE", "number": 91, "salary": "-", "experience": null, "image": "https://media.api-sports.io/american-football/players/14296.png"}, {"id": 14488, "name": "Adonai Mitchell", "age": 22, "height": "6' 2\"", "weight": "205 lbs", "college": "Texas", "group": "Offense", "position": "WR", "number": 10, "salary": "-", "experience": 2, "image": "https://media.api-sports.io/american-football/players/14488.png"}, {"id": 14854, "name": "Anthony Richardson", "age": 23, "height": "6' 4\"", "weight": "244 lbs", "college": "Florida", "group": "Offense", "position": "QB", "number": 5, "salary": null, "experience": 3, "image": "https://media.api-sports.io/american-football/players/14854.png"}, {"id": 14863, "name": "Nay'Quan Wright", "age": 25, "height": "5' 9\"", "weight": "193 lbs", "college": "South Florida", "group": "Offense", "position": "RB", "number": 42, "salary": "-", "experience": null, "image": "https://media.api-sports.io/american-football/players/14863.png"}, {"id": 16050, "name": "Will Mallory", "age": 26, "height": "6' 4\"", "weight": "239 lbs", "college": "Miami", "group": "Offense", "position": "TE", "number": 86, "salary": "-", "experience": 3, "image": "https://media.api-sports.io/american-football/players/16050.png"}, {"id": 16315, "name": "Jake Chaney", "age": null, "height": "5' 11\"", "weight": "233 lbs", "college": "Wisconsin", "group": "Defense", "position": "LB", "number": 47, "salary": "-", "experience": null, "image": "https://media.api-sports.io/american-football/players/16315.png"}, {"id": 16354, "name": "Hunter Wohler", "age": 22, "height": "6' 2\"", "weight": "213 lbs", "college": "Wisconsin", "group": "Injured Reserve Or O", "position": "S", "number": 30, "salary": "-", "experience": null, "image": "https://media.api-sports.io/american-football/players/16354.png"}, {"id": 16944, "name": "Ulysses Bentley IV", "age": 24, "height": "5' 10\"", "weight": "200 lbs", "college": "Ole Miss", "group": "Practice Squad", "position": "RB", "number": 37, "salary": null, "experience": null, "image": "https://media.api-sports.io/american-football/players/16944.png"}, {"id": 17060, "name": "Ladarius Tennison", "age": 24, "height": "5' 10\"", "weight": "207 lbs", "college": "UCF", "group": "Defense", "position": "S", "number": 43, "salary": "-", "experience": null, "image": "https://media.api-sports.io/american-football/players/17060.png"}, {"id": 17062, "name": "Trey Washington", "age": 22, "height": "5' 10\"", "weight": "205 lbs", "college": "Ole Miss", "group": "Practice Squad", "position": "S", "number": 41, "salary": null, "experience": null, "image": "https://media.api-sports.io/american-football/players/17062.png"}, {"id": 17431, "name": "Ajou Ajou", "age": 23, "height": "6' 3\"", "weight": "218 lbs", "college": "Garden City CC KS", "group": "Offense", "position": "WR", "number": 9, "salary": "-", "experience": null, "image": "https://media.api-sports.io/american-football/players/17431.png"}, {"id": 17527, "name": "Spencer Shrader", "age": 26, "height": "6' 2\"", "weight": "201 lbs", "college": "Notre Dame", "group": "Special Teams", "position": "PK", "number": 3, "salary": "-", "experience": 2, "image": "https://media.api-sports.io/american-football/players/17527.png"}, {"id": 18062, "name": "Durell Nchami", "age": 25, "height": "6' 4\"", "weight": "258 lbs", "college": "Maryland", "group": "Practice Squad", "position": "DE", "number": 74, "salary": null, "experience": 1, "image": "https://media.api-sports.io/american-football/players/18062.png"}, {"id": 18455, "name": "Nate Noel", "age": 23, "height": "5' 9\"", "weight": "200 lbs", "college": "Missouri", "group": "Offense", "position": "RB", "number": 41, "salary": "-", "experience": null, "image": "https://media.api-sports.io/american-football/players/18455.png"}, {"id": 19598, "name": "Laiatu Latu", "age": 24, "height": "6' 5\"", "weight": "265 lbs", "college": "UCLA", "group": "Defense", "position": "DE", "number": 97, "salary": "-", "experience": 2, "image": "https://media.api-sports.io/american-football/players/19598.png"}, {"id": 19616, "name": "Alex Johnson", "age": 24, "height": "6' 0\"", "weight": "185 lbs", "college": "UCLA", "group": "Defense", "position": "CB", "number": 39, "salary": "-", "experience": 1, "image": "https://media.api-sports.io/american-football/players/19616.png"}, {"id": 20533, "name": "Daniel Scott", "age": 26, "height": "6' 1\"", "weight": "208 lbs", "college": "California", "group": "Defense", "position": "S", "number": 32, "salary": "-", "experience": 3, "image": "https://media.api-sports.io/american-football/players/20533.png"}, {"id": 21901, "name": "DJ Giddens", "age": 22, "height": "6' 0\"", "weight": "212 lbs", "college": "Kansas State", "group": "Offense", "position": "RB", "number": 21, "salary": "-", "experience": null, "image": "https://media.api-sports.io/american-football/players/21901.png"}, {"id": 21986, "name": "Julius Brents", "age": 25, "height": "6' 3\"", "weight": "198 lbs", "college": "Kansas State", "group": "Defense", "position": "CB", "number": 0, "salary": null, "experience": 3, "image": "https://media.api-sports.io/american-football/players/21986.png"}, {"id": 25316, "name": "Anthony Gould", "age": 24, "height": "5' 8\"", "weight": "174 lbs", "college": "Oregon State", "group": "Offense", "position": "WR", "number": 6, "salary": "-", "experience": 2, "image": "https://media.api-sports.io/american-football/players/25316.png"}, {"id": 25820, "name": "Desmond Little", "age": 25, "height": "6' 4\"", "weight": "242 lbs", "college": "UAB", "group": "Defense", "position": "DE", "number": 78, "salary": "-", "experience": null, "image": "https://media.api-sports.io/american-football/players/25820.png"}, {"id": 27067, "name": "Johnathan Edwards", "age": 23, "height": "6' 1\"", "weight": "201 lbs", "college": "Tulane", "group": "Defense", "position": "CB", "number": 35, "salary": "-", "experience": null, "image": "https://media.api-sports.io/american-football/players/27067.png"}, {"id": 27515, "name": "Brian Mayes", "age": 22, "height": "6' 0\"", "weight": "187 lbs", "college": "Texas A&M", "group": "Defense", "position": "CB", "number": 36, "salary": null, "experience": null, "image": "https://media.api-sports.io/american-football/players/27515.png"}, {"id": 29175, "name": "Landon Parker", "age": 25, "height": "6' 2\"", "weight": "211 lbs", "college": "Troy", "group": "Offense", "position": "WR", "number": 8, "salary": "-", "experience": null, "image": "https://media.api-sports.io/american-football/players/29175.png"}, {"id": 29288, "name": "Blayne Taylor", "age": 23, "height": "6' 4\"", "weight": "212 lbs", "college": "Abilene Christian", "group": "Offense", "position": "WR", "number": 4, "salary": "-", "experience": null, "image": "https://media.api-sports.io/american-football/players/29288.png"}, {"id": 33865, "name": "Devonta Davis", "age": 24, "height": "6' 3\"", "weight": "300 lbs", "college": "Florida Atlantic", "group": "Defense", "position": "DT", "number": 61, "salary": "-", "experience": null, "image": "https://media.api-sports.io/american-football/players/33865.png"}, {"id": 34591, "name": "Joseph Vaughn", "age": null, "height": "6' 3\"", "weight": "238 lbs", "college": "UCLA", "group": "Defense", "position": "LB", "number": 49, "salary": "-", "experience": null, "image": "https://media.api-sports.io/american-football/players/34591.png"}, {"id": 59047, "name": "Tyler Kahmann", "age": 24, "height": "6' 2\"", "weight": "207 lbs", "college": "Emporia State", "group": "Practice Squad", "position": "WR", "number": 43, "salary": null, "experience": null, "image": "https://media.api-sports.io/american-football/players/59047.png"}]}